sprt_jira_processor/__init__.py
sprt_jira_processor/ai_integration.py
sprt_jira_processor/jira_interaction.py
sprt_jira_processor/processor.py
sprt_jira_processor/utils.py
sprt_jira_processor-0.1.4.dist-info/licenses/LICENSE
sprt_jira_processor-0.1.4.dist-info/METADATA
sprt_jira_processor-0.1.4.dist-info/WHEEL
sprt_jira_processor-0.1.4.dist-info/top_level.txt
sprt_jira_processor-0.1.4.dist-info/RECORD
