Metadata-Version: 2.4
Name: sprt_jira_processor
Version: 0.1.4
Summary: A library to process JIRA issues and generate summaries.
Author: hannah biju
Author-email: hb7379@zebra.com
Classifier: Programming Language :: Python :: 3
Classifier: License :: OSI Approved :: MIT License
Classifier: Operating System :: OS Independent
Requires-Python: >=3.6
License-File: LICENSE
Requires-Dist: jira
Requires-Dist: python-dotenv
Requires-Dist: openai
Requires-Dist: pandas
Dynamic: author
Dynamic: author-email
Dynamic: classifier
Dynamic: license-file
Dynamic: requires-dist
Dynamic: requires-python
Dynamic: summary
